aiida_fireball/__init__.py
aiida_fireball/_version.py
aiida_fireball/calculations/__init__.py
aiida_fireball/calculations/birch_murnaghan_fit.py
aiida_fireball/calculations/fireball.py
aiida_fireball/calculations/utils.py
aiida_fireball/calculations/structure/__init__.py
aiida_fireball/calculations/structure/tools.py
aiida_fireball/parsers/__init__.py
aiida_fireball/parsers/fireball.py
aiida_fireball/parsers/raw.py
aiida_fireball/workflows/__init__.py
aiida_fireball/workflows/birch_murnaghan_relax.py
aiida_fireball/workflows/transport_calc.py
aiida_fireball-1.0.2.dist-info/METADATA
aiida_fireball-1.0.2.dist-info/WHEEL
aiida_fireball-1.0.2.dist-info/entry_points.txt
aiida_fireball-1.0.2.dist-info/licenses/LICENSE
aiida_fireball-1.0.2.dist-info/RECORD
