Metadata-Version: 2.4
Name: aiida-fireball
Version: 1.0.2
Summary: AiiDA plugin for Fireball
Project-URL: Homepage, https://github.com/mohamedmamlouk/aiida-fireball
Project-URL: Source, https://github.com/mohamedmamlouk/aiida-fireball
Project-URL: Documentation, https://aiida-fireball.readthedocs.io/
Project-URL: Issues, https://github.com/mohamedmamlouk/aiida-fireball/issues
Author-email: Valk Scripter <valkscode@gmail.com>, mamloukmohamed <mohamedmamlouk@example.com>
License: MIT License
License-File: LICENSE
Keywords: aiida,plugin
Classifier: Development Status :: 3 - Alpha
Classifier: Framework :: AiiDA
Classifier: Intended Audience :: Science/Research
Classifier: License :: OSI Approved :: MIT License
Classifier: Natural Language :: English
Classifier: Programming Language :: Python
Classifier: Programming Language :: Python :: 3
Classifier: Programming Language :: Python :: 3.9
Classifier: Programming Language :: Python :: 3.10
Classifier: Programming Language :: Python :: 3.11
Classifier: Programming Language :: Python :: 3.12
Requires-Python: >=3.9
Requires-Dist: aiida-core<3,>=2.5
Requires-Dist: aiida-pseudo~=1.1
Requires-Dist: ase
Requires-Dist: click~=8.0
Requires-Dist: importlib-resources
Requires-Dist: jsonschema
Requires-Dist: numpy
Requires-Dist: packaging
Requires-Dist: pydantic~=2.0
Requires-Dist: pymc
Requires-Dist: voluptuous
Requires-Dist: xmlschema~=2.0
Provides-Extra: docs
Requires-Dist: linkify-it-py; extra == 'docs'
Requires-Dist: myst-parser~=1.0.0; extra == 'docs'
Requires-Dist: sphinx-autoapi~=3.0; extra == 'docs'
Requires-Dist: sphinx-book-theme~=1.0.1; extra == 'docs'
Requires-Dist: sphinx-click~=4.4.0; extra == 'docs'
Requires-Dist: sphinx-copybutton~=0.5.2; extra == 'docs'
Requires-Dist: sphinx-design~=0.4.1; extra == 'docs'
Requires-Dist: sphinx-rtd-theme; extra == 'docs'
Requires-Dist: sphinxcontrib-details-directive~=0.1.0; extra == 'docs'
Requires-Dist: sphinx~=6.2.1; extra == 'docs'
Provides-Extra: pre-commit
Requires-Dist: hatch; extra == 'pre-commit'
Requires-Dist: pre-commit~=2.17; extra == 'pre-commit'
Requires-Dist: pylint-aiida~=0.1.1; extra == 'pre-commit'
Requires-Dist: pylint~=2.17.2; extra == 'pre-commit'
Requires-Dist: toml; extra == 'pre-commit'
Provides-Extra: tests
Requires-Dist: pgtest; extra == 'tests'
Requires-Dist: pytest-cov; extra == 'tests'
Requires-Dist: pytest-regressions; extra == 'tests'
Requires-Dist: pytest~=7.0; extra == 'tests'
